readDataFile/ReadDataFile.py
readDataFile/_ListDelimiter_.py
readDataFile/__init__.py
readDataFile-0.0.9.dist-info/LICENSE.txt
readDataFile-0.0.9.dist-info/METADATA
readDataFile-0.0.9.dist-info/WHEEL
readDataFile-0.0.9.dist-info/top_level.txt
readDataFile-0.0.9.dist-info/RECORD
