Metadata-Version: 2.1
Name: readDataFile
Version: 0.0.9
Summary: uno test data file read
Home-page: https://github.com/uunnooo/readUnoDataFile
Author: Uno
Author-email: uno0522@gmail.com
Project-URL: Bug Tracker, https://github.com/uunnooo/readUnoDataFile
Classifier: Programming Language :: Python :: 3
Classifier: License :: OSI Approved :: MIT License
Classifier: Operating System :: OS Independent
Requires-Python: >=3.6
License-File: LICENSE.txt
